impaction_ai/__init__.py
impaction_ai/api_client.py
impaction_ai/buffer_storage.py
impaction_ai/client.py
impaction_ai/config.py
impaction_ai/constants.py
impaction_ai/exception.py
impaction_ai/ingestion/v1alpha/event_pb2.py
impaction_ai/ingestion/v1alpha/event_pb2.pyi
impaction_ai/ingestion/v1alpha/event_pb2_grpc.py
impaction_ai/ingestion/v1alpha/ingestion_pb2.py
impaction_ai/ingestion/v1alpha/ingestion_pb2.pyi
impaction_ai/ingestion/v1alpha/ingestion_pb2_grpc.py
impaction_ai/integration/langchain.py
impaction_ai/integration/llama_index.py
impaction_ai/logger.py
impaction_ai/utils.py
impaction_ai/worker.py
impaction_ai-0.2.3.dist-info/LICENSE
impaction_ai-0.2.3.dist-info/METADATA
impaction_ai-0.2.3.dist-info/WHEEL
impaction_ai-0.2.3.dist-info/RECORD
