Metadata-Version: 2.1
Name: impaction-ai
Version: 0.2.3
Summary: Python SDK for impaction.ai
Author: Coxwave
Author-email: tech@coxwave.com
Requires-Python: >=3.8.0,<4.0
Classifier: Programming Language :: Python :: 3
Classifier: Programming Language :: Python :: 3.8
Classifier: Programming Language :: Python :: 3.9
Classifier: Programming Language :: Python :: 3.10
Classifier: Programming Language :: Python :: 3.11
Requires-Dist: google-api-python-client (>=2.98.0,<3.0.0)
Requires-Dist: pendulum (>=2.1.2,<3.0.0)
Requires-Dist: protobuf (>=4.24.2,<5.0.0)
Requires-Dist: requests (>=2.31.0,<3.0.0)
